{"cameraMode":{"drawMode":0,"name":"Shaded","section":"Shading Mode"},"sceneLighting":true,"audioPlay":false,"sceneViewState":{"m_AlwaysRefresh":false,"showFog":true,"showSkybox":true,"showFlares":true,"showImageEffects":true,"showParticleSystems":true,"showVisualEffectGraphs":true,"m_FxEnabled":true},"in2DMode":false,"pivot":{"x":-20.293750762939454,"y":0.45333588123321535,"z":-12.68904972076416},"rotation":{"x":-0.34502533078193667,"y":-0.3231198787689209,"z":0.12786754965782166,"w":-0.8718987107276917},"size":32.561222076416019,"orthographic":false}